bigml/__init__.py
bigml/anomaly.py
bigml/api.py
bigml/association.py
bigml/associationrule.py
bigml/basemodel.py
bigml/bigmlconnection.py
bigml/centroid.py
bigml/cluster.py
bigml/constants.py
bigml/dataset.py
bigml/deepnet.py
bigml/domain.py
bigml/ensemble.py
bigml/ensemblepredictor.py
bigml/evaluation.py
bigml/exceptions.py
bigml/execution.py
bigml/featurizer.py
bigml/fields.py
bigml/flatline.py
bigml/flattree.py
bigml/fusion.py
bigml/io.py
bigml/item.py
bigml/linear.py
bigml/local_model.py
bigml/logistic.py
bigml/model.py
bigml/modelfields.py
bigml/multimodel.py
bigml/multivote.py
bigml/multivotelist.py
bigml/path.py
bigml/pca.py
bigml/predicate.py
bigml/predicates.py
bigml/prediction.py
bigml/shapwrapper.py
bigml/supervised.py
bigml/timeseries.py
bigml/topicmodel.py
bigml/tree_utils.py
bigml/tsoutconstants.py
bigml/tssubmodels.py
bigml/util.py
bigml/version.py
bigml/webhooks.py
bigml/api_handlers/__init__.py
bigml/api_handlers/anomalyhandler.py
bigml/api_handlers/anomalyscorehandler.py
bigml/api_handlers/associationhandler.py
bigml/api_handlers/associationsethandler.py
bigml/api_handlers/batchanomalyscorehandler.py
bigml/api_handlers/batchcentroidhandler.py
bigml/api_handlers/batchpredictionhandler.py
bigml/api_handlers/batchprojectionhandler.py
bigml/api_handlers/batchtopicdistributionhandler.py
bigml/api_handlers/centroidhandler.py
bigml/api_handlers/clusterhandler.py
bigml/api_handlers/configurationhandler.py
bigml/api_handlers/correlationhandler.py
bigml/api_handlers/datasethandler.py
bigml/api_handlers/deepnethandler.py
bigml/api_handlers/ensemblehandler.py
bigml/api_handlers/evaluationhandler.py
bigml/api_handlers/executionhandler.py
bigml/api_handlers/externalconnectorhandler.py
bigml/api_handlers/forecasthandler.py
bigml/api_handlers/fusionhandler.py
bigml/api_handlers/libraryhandler.py
bigml/api_handlers/linearhandler.py
bigml/api_handlers/logistichandler.py
bigml/api_handlers/modelhandler.py
bigml/api_handlers/optimlhandler.py
bigml-9.8.3.dist-info/LICENSE
bigml-9.8.3.dist-info/METADATA
bigml-9.8.3.dist-info/WHEEL
bigml-9.8.3.dist-info/top_level.txt
bigml-9.8.3.dist-info/RECORD
