Metadata-Version: 2.2
Name: bigml
Version: 9.8.3
Summary: An open source binding to BigML.io, the public BigML API
Home-page: https://bigml.com/developers
Download-URL: https://github.com/bigmlcom/python
Author: The BigML Team
Author-email: bigml@bigml.com
License: http://www.apache.org/licenses/LICENSE-2.0
Classifier: Development Status :: 4 - Beta
Classifier: Intended Audience :: Developers
Classifier: License :: OSI Approved :: Apache Software License
Classifier: Natural Language :: English
Classifier: Operating System :: OS Independent
Classifier: Programming Language :: Python
Classifier: Programming Language :: Python :: 3
Classifier: Topic :: Software Development :: Libraries :: Python Modules
License-File: LICENSE
Requires-Dist: setuptools==70.0.0
Requires-Dist: unidecode
Requires-Dist: bigml-chronos>=0.4.3
Requires-Dist: requests
Requires-Dist: requests-toolbelt
Requires-Dist: msgpack
Requires-Dist: numpy>=1.22
Requires-Dist: scipy
Requires-Dist: javascript
Provides-Extra: images
Requires-Dist: bigml-sensenet==0.7.5; extra == "images"
Provides-Extra: topics
Requires-Dist: cython; extra == "topics"
Requires-Dist: pystemmer==2.2.0.1; extra == "topics"
Provides-Extra: full
Requires-Dist: bigml-sensenet==0.7.5; extra == "full"
Requires-Dist: cython; extra == "full"
Requires-Dist: pystemmer==2.2.0.1; extra == "full"
Dynamic: author
Dynamic: author-email
Dynamic: classifier
Dynamic: description
Dynamic: download-url
Dynamic: home-page
Dynamic: license
Dynamic: provides-extra
Dynamic: requires-dist
Dynamic: summary
